LAB4/QUES1/q1.v
module q1(w,en,op);
input[1:0]w;
input en;
output reg[3:0]op;
always@(w,en)
begin
if(en==0 && w==0)
op=1;
else if(en==0 && w==1)
op=2;
else if(en==0 && w==2)
op=4;
else if(en==0 && w==3)
op=8;
else
op=0;
end
endmodule

LAB4/QUES1/q1_tb.v
`timescale 1ns/1ns
`include "q1.v"
module q1_tb;
reg[1:0]w;
reg en;
wire [3:0]op;
q1 dto4(w,en,op);
initial
begin
$dumpfile("q1_tb.vcd");
$dumpvars(op,q1_tb);
en=1'b0 ;w=2'b00 ;
#20;
en=1'b0 ;w=2'b01 ;
#20;
en=1'b0 ;w=2'b10 ;
#20;
en=1'b0 ;w=2'b11 ;
#20;
en=1'b1 ;w=2'b00 ;
#20;
en=1'b1 ;w=2'b01 ;
#20;
en=1'b1 ;w=2'b10 ;
#20;
en=1'b1 ;w=2'b11 ;
#20;

$display("Test complete");
end
endmodule

LAB4/QUES1/q1_tb.vcd
$date
	Sat Aug 31 09:40:43 2024
$end
$version
	Icarus Verilog
$end
$timescale
	1ns
$end
$scope module q1_tb $end
$var wire 4 ! op [3:0] $end
$var reg 1 " en $end
$var reg 2 # w [1:0] $end
$scope module dto4 $end
$var wire 1 " en $end
$var wire 2 $ w [1:0] $end
$var reg 4 % op [3:0] $end
$upscope $end
$upscope $end
$enddefinitions $end
#0
$dumpvars
b1 %
b0 $
b0 #
0"
b1 !
$end
#20
b10 !
b10 %
b1 #
b1 $
#40
b100 !
b100 %
b10 #
b10 $
#60
b1000 !
b1000 %
b11 #
b11 $
#80
b0 !
b0 %
b0 #
b0 $
1"
#100
b1 #
b1 $
#120
b10 #
b10 $
#140
b11 #
b11 $
