LAB9/ex/sync.v
module tff (Q, T, clear, clk);
input T,clear, clk;
output reg Q;
always @ (posedge clk or negedge clear)
begin
if ( clear==0)
Q<=0;
else if ( T==1)
Q<=~Q;
else Q<=Q;
end
endmodule

module sync(clear, clk, Q);
input clear, clk;
output [2:0] Q;
wire w1, w2, w3;
tff FF0 (Q[0], 1'b1, clear, clk);
tff FF1 (Q[1], w1 , clear, clk);
tff FF2 (Q[2], w3, clear, clk);
nand G0 (w1,1'b1, Q[0]);
nand G1 (w2,1'b1, Q[1]);
and G2 (w3, w1, w2);
endmodule

LAB9/ex/sync_tb.v
`timescale 1ns/1ns
`include "sync.v"
//Name of the Verilog file
module sync_tb;
reg clear, clk;
wire [2:0] Q;
// Instanstiation
sync G0 (clear, clk, Q);
always #5 clk=~clk;
initial
begin
clear=0;
clk=1;
#150 $finish;
end
initial
begin
$dumpfile("sync_tb.vcd");
$dumpvars(0,sync_tb);
$monitor($time, " clear=%b, Q=%3b", clear, Q );
#12 clear =1;
end
endmodule

LAB9/ex/sync_tb.vcd
$date
	Tue Oct  8 10:26:35 2024
$end
$version
	Icarus Verilog
$end
$timescale
	1ns
$end
$scope module sync_tb $end
$var wire 3 ! Q [2:0] $end
$var reg 1 " clear $end
$var reg 1 # clk $end
$scope module G0 $end
$var wire 1 " clear $end
$var wire 1 # clk $end
$var wire 1 $ w1 $end
$var wire 1 % w2 $end
$var wire 1 & w3 $end
$var wire 3 ' Q [2:0] $end
$scope module FF0 $end
$var wire 1 ( T $end
$var wire 1 " clear $end
$var wire 1 # clk $end
$var reg 1 ) Q $end
$upscope $end
$scope module FF1 $end
$var wire 1 $ T $end
$var wire 1 " clear $end
$var wire 1 # clk $end
$var reg 1 * Q $end
$upscope $end
$scope module FF2 $end
$var wire 1 & T $end
$var wire 1 " clear $end
$var wire 1 # clk $end
$var reg 1 + Q $end
$upscope $end
$upscope $end
$upscope $end
$enddefinitions $end
#0
$dumpvars
0+
0*
0)
1(
b0 '
1&
1%
1$
1#
0"
b0 !
$end
#5
0#
#10
1#
#12
1"
#15
0#
#20
0&
0$
0%
1)
1*
b111 !
b111 '
1+
1#
#25
0#
#30
1$
b110 !
b110 '
0)
1#
#35
0#
#40
0$
1%
1)
b101 !
b101 '
0*
1#
#45
0#
#50
1&
1$
b100 !
b100 '
0)
1#
#55
0#
#60
0&
0$
0%
1)
1*
b11 !
b11 '
0+
1#
#65
0#
#70
1$
b10 !
b10 '
0)
1#
#75
0#
#80
0$
1%
1)
b1 !
b1 '
0*
1#
#85
0#
#90
1&
1$
b0 !
b0 '
0)
1#
#95
0#
#100
0&
0$
0%
1)
1*
b111 !
b111 '
1+
1#
#105
0#
#110
1$
b110 !
b110 '
0)
1#
#115
0#
#120
0$
1%
1)
b101 !
b101 '
0*
1#
#125
0#
#130
1&
1$
b100 !
b100 '
0)
1#
#135
0#
#140
0&
0$
0%
1)
1*
b11 !
b11 '
0+
1#
#145
0#
#150
1$
b10 !
b10 '
0)
1#
