LAB6/q1/dflipflop.v
module dflipflop (
    input  logic clk,
    input  logic reset,
    input  logic d,
    output logic q
);

always @(posedge clk) begin
    if (reset) begin
        q <= 1'b0;
    end 
    else begin
        q <= d;
    end
end

endmodule

LAB6/q1/dflipflop_tb.v
`timescale 1ns/1ns
`include "dflipflop.v"
module dflipflop_tb();

reg clk;
reg reset;
reg d;
wire q;

dflipflop fxn (clk, reset, d, q);

initial begin
    $dumpfile("dflipflop_tb.vcd");
    $dumpvars(0, dflipflop_tb);
    end
    initial begin
    clk = 0;
 forever #20 clk=~clk;
end

initial begin
d=0; reset=0; #20;
d=1; reset=0; #20;
d=0; reset=0; #20;
d=1; reset=0; #20;
d=0; reset=0; #20;
d=1; reset=1; #20;
d=1; reset=0; #20;
d=1; reset=0; #20;

#160 $finish;
$display("Test complete");
end
endmodule

LAB6/q1/dflipflop_tb.vcd
$date
	Sat Sep 14 10:05:50 2024
$end
$version
	Icarus Verilog
$end
$timescale
	1ns
$end
$scope module dflipflop_tb $end
$var wire 1 ! q $end
$var reg 1 " clk $end
$var reg 1 # d $end
$var reg 1 $ reset $end
$scope module fxn $end
$var wire 1 " clk $end
$var wire 1 # d $end
$var wire 1 $ reset $end
$var reg 1 ! q $end
$upscope $end
$upscope $end
$enddefinitions $end
#0
$dumpvars
0$
0#
0"
x!
$end
#20
1!
1#
1"
#40
0#
0"
#60
1#
1"
#80
0#
0"
#100
0!
1$
1#
1"
#120
0$
0"
#140
1!
1"
