LAB2/QUES2/question2.v
module question2(A,B,Cin,Sum,Carry);
input A,B,Cin;
output Sum,Carry;
assign Sum= A ^ B ^ Cin;
assign Carry=(A & B)|(B & Cin)|(Cin & A);

endmodule

LAB2/QUES2/question2_tb.v
`timescale 1ns/1ns
`include "question2.v"

module question2_tb();
reg A,B,Cin;
wire Sum,Carry;

question2 q2(A,B,Cin,Sum,Carry);

initial
begin
$dumpfile("question2_tb.vcd");
$dumpvars(0, question2_tb);

A=1'b0; B=1'b0; Cin=1'b0; 
#20;
A=1'b0; B=1'b0; Cin=1'b1; 
#20;
A=1'b0; B=1'b1; Cin=1'b0; 
#20;
A=1'b0; B=1'b1; Cin=1'b1; 
#20;
A=1'b1; B=1'b0; Cin=1'b0; 
#20;
A=1'b1; B=1'b0; Cin=1'b1; 
#20;
A=1'b1; B=1'b1; Cin=1'b0; 
#20;
A=1'b1; B=1'b1; Cin=1'b1; 
#20;

$display("Test complete");
end
endmodule

LAB2/QUES2/question2_tb.vcd
$date
	Sat Aug 10 09:39:31 2024
$end
$version
	Icarus Verilog
$end
$timescale
	1ns
$end
$scope module question2_tb $end
$var wire 1 ! Sum $end
$var wire 1 " Carry $end
$var reg 1 # A $end
$var reg 1 $ B $end
$var reg 1 % Cin $end
$scope module q2 $end
$var wire 1 # A $end
$var wire 1 $ B $end
$var wire 1 " Carry $end
$var wire 1 % Cin $end
$var wire 1 ! Sum $end
$upscope $end
$upscope $end
$enddefinitions $end
#0
$dumpvars
0%
0$
0#
0"
0!
$end
#20
1!
1%
#40
0%
1$
#60
1"
0!
1%
#80
0"
1!
0%
0$
1#
#100
1"
0!
1%
#120
0%
1$
#140
1!
1%
