LAB1/add1/A1.v
module A1(x1,x2,x3,f1,f2);
input x1,x2,x3;
output f1,f2;
assign f1 = (x1 & ~x3) | (x2 & x3) | (~x2 & ~x3);
assign f2 = (x1 | ~x2 | x3) & (x1 | x2 | ~x3) & (~x1 | x2 | ~x3);
endmodule

LAB1/add1/A1_tb.v
`timescale 1ns/1ns
`include "A1.v"

module A1_tb();
reg x1,x2,x3;

wire f1,f2;

A1 OUT1(x1, x2, x3, f1, f2);


initial
begin
$dumpfile("A1_tb.vcd");
$dumpvars(0, A1_tb);

x1=1'b0; x2=1'b0; x3=1'b0;
#20;
x1=1'b0; x2=1'b0; x3=1'b1;
#20;
x1=1'b0; x2=1'b1; x3=1'b0;
#20;
x1=1'b0; x2=1'b1; x3=1'b1;
#20;
x1=1'b1; x2=1'b0; x3=1'b0;
#20;
x1=1'b1; x2=1'b0; x3=1'b1;
#20;
x1=1'b1; x2=1'b1; x3=1'b0;
#20;
x1=1'b1; x2=1'b1; x3=1'b1;
#20;
$display("Test complete");
end
endmodule

LAB1/add1/A1_tb.vcd
$date
	Sat Aug  3 09:57:21 2024
$end
$version
	Icarus Verilog
$end
$timescale
	1ns
$end
$scope module A1_tb $end
$var wire 1 ! f2 $end
$var wire 1 " f1 $end
$var reg 1 # x1 $end
$var reg 1 $ x2 $end
$var reg 1 % x3 $end
$scope module OUT1 $end
$var wire 1 " f1 $end
$var wire 1 ! f2 $end
$var wire 1 # x1 $end
$var wire 1 $ x2 $end
$var wire 1 % x3 $end
$upscope $end
$upscope $end
$enddefinitions $end
#0
$dumpvars
0%
0$
0#
1"
1!
$end
#20
0!
0"
1%
#40
0!
0%
1$
#60
1"
1!
1%
#80
0%
0$
1#
#100
0"
0!
1%
#120
1"
1!
0%
1$
#140
1%
