LAB8/q2/seq1010.v
module dff(d,clk,q);
	input d,clk;
	output reg q=0;
	always @(posedge clk)
		q<=d;
endmodule
module seq1010(clk,w,state,z);
	input clk,w;
	output [1:0]state;
	output z;
	wire d1,d0;
	assign d1=(~w&state[0])|(w&state[1]&(~state[0]));
	assign d0=w;
	assign z=~w&state[1]&state[0];
	dff ff1(d1,clk,state[1]);
	dff ff0(d0,clk,state[0]);
endmodule

LAB8/q2/seq1010_tb.v
`timescale 1ns/1ns
`include "seq1010.v"
module seq1010_tb();
	reg clk;
	reg w;
	wire[1:0]state;
	wire z;
	seq1010 mod(clk,w,state,z);
	always #10 clk=~clk;
	initial begin
	clk=0;w=0;
	$dumpfile("seq1010_tb.vcd");
	$dumpvars(0,seq1010_tb);
	#10 w=0;
	#10 w=0;
	#10 w=1;
	#10 w=0;
	#10 w=1;
	#10 w=0;
	#10 w=1;
	#10 w=0;
	#10 w=1;
	#10 w=1;
	#200 $finish;
	$display("Test complete");
	end
	endmodule

LAB8/q2/seq1010_tb.vcd
$date
	Sat Oct  5 10:56:06 2024
$end
$version
	Icarus Verilog
$end
$timescale
	1ns
$end
$scope module seq1010_tb $end
$var wire 1 ! z $end
$var wire 2 " state [1:0] $end
$var reg 1 # clk $end
$var reg 1 $ w $end
$scope module mod $end
$var wire 1 # clk $end
$var wire 1 % d0 $end
$var wire 1 & d1 $end
$var wire 1 $ w $end
$var wire 1 ! z $end
$var wire 2 ' state [1:0] $end
$scope module ff0 $end
$var wire 1 # clk $end
$var wire 1 % d $end
$var reg 1 ( q $end
$upscope $end
$scope module ff1 $end
$var wire 1 # clk $end
$var wire 1 & d $end
$var reg 1 ) q $end
$upscope $end
$upscope $end
$upscope $end
$enddefinitions $end
#0
$dumpvars
0)
0(
b0 '
0&
0%
0$
0#
b0 "
0!
$end
#10
1#
#20
0#
#30
b1 "
b1 '
1(
1%
1$
1#
#40
1&
0%
0$
0#
#50
b11 "
b11 '
1)
0&
1%
1$
1#
#60
1&
1!
0%
0$
0#
#70
0&
0!
1%
1$
1#
#80
1&
1!
0%
0$
0#
#90
0&
0!
1%
1$
1#
#100
0#
#110
b1 "
b1 '
0)
1#
