LAB6/q2/tflipflop.v
module tflipflop (
    input  logic clk,
    input  logic reset,
    input  logic t,
    output logic q
);
initial begin
q=1'b0;
end

always @(negedge clk) begin
    if (~reset) begin
        q <= 1'b0;
        end
    else if (t) 
    begin
        q <= ~q;
        end
        else
         begin
        q<=q; 
        end
        end
endmodule

LAB6/q2/tflipflop_tb.v
`timescale 1ns/1ns
`include "tflipflop.v"
module tflipflop_tb();

reg clk;
reg reset;
reg t;
wire q;


tflipflop fxn(
    .clk(clk), 
    .reset(reset), 
    .t(t), 
    .q(q)
);

initial begin
    $dumpfile("tflipflop_tb.vcd");
    $dumpvars(0, tflipflop_tb);
    end
    initial begin
    clk = 0;
  forever #20 clk=~clk;
  end
  initial begin
t=1; reset=1 ;#20;
t=0; reset=1 ;#20;
t=1; reset=1 ;#20;
t=1; reset=0 ;#20;
t=1; reset=1 ;#20;
t=1; reset=1 ;#20;
t=0; reset=0 ;#20;
t=1; reset=1 ;#20;

#200 $finish;
$display("Done");

end
endmodule

LAB6/q2/tflipflop_tb.vcd
$date
	Sat Sep 14 10:36:51 2024
$end
$version
	Icarus Verilog
$end
$timescale
	1ns
$end
$scope module tflipflop_tb $end
$var wire 1 ! q $end
$var reg 1 " clk $end
$var reg 1 # reset $end
$var reg 1 $ t $end
$scope module fxn $end
$var wire 1 " clk $end
$var wire 1 # reset $end
$var wire 1 $ t $end
$var reg 1 ! q $end
$upscope $end
$upscope $end
$enddefinitions $end
#0
$dumpvars
1$
1#
0"
1!
$end
#20
0$
1"
#40
0!
1$
0"
#60
0#
1"
#80
1!
1#
0"
#100
1"
#120
0!
0#
0$
0"
#140
1#
1$
1"
#160
1!
0"
#180
1"
#200
0!
0"
#220
1"
#240
1!
0"
#260
1"
#280
0!
0"
#300
1"
#320
1!
0"
#340
1"
#360
0!
0"
