LAB2/QUES1/question1.v
module question1(A,B,C,D,f);
input A,B,C,D;
output f;
assign g=(~C & ~D);
assign h=(~A | ~B);
assign f = (g & h)|(~g & ~h);

endmodule

LAB2/QUES1/question1_tb.v
`timescale 1ns/1ns
`include "question1.v"

module question1_tb();
reg A,B,C,D;
wire f;

question1 q1(A,B,C,D,f);

initial
begin
$dumpfile("question1_tb.vcd");
$dumpvars(0, question1_tb);

A=1'b0; B=1'b0; C=1'b0; D=1'b0;
#20;
A=1'b0; B=1'b0; C=1'b0; D=1'b1;
#20;
A=1'b0; B=1'b0; C=1'b1; D=1'b0;
#20;
A=1'b0; B=1'b0; C=1'b1; D=1'b1;
#20;
A=1'b0; B=1'b1; C=1'b0; D=1'b0;
#20;
A=1'b0; B=1'b1; C=1'b0; D=1'b1;
#20;
A=1'b0; B=1'b1; C=1'b1; D=1'b0;
#20;
A=1'b0; B=1'b1; C=1'b1; D=1'b1;
#20;
A=1'b1; B=1'b0; C=1'b0; D=1'b0;
#20;
A=1'b1; B=1'b0; C=1'b0; D=1'b1;
#20;
A=1'b1; B=1'b0; C=1'b1; D=1'b0;
#20;
A=1'b1; B=1'b0; C=1'b1; D=1'b1;
#20;
A=1'b1; B=1'b1; C=1'b0; D=1'b0;
#20;
A=1'b1; B=1'b1; C=1'b0; D=1'b1;
#20;
A=1'b1; B=1'b1; C=1'b1; D=1'b0;
#20;
A=1'b1; B=1'b1; C=1'b1; D=1'b1;
#20;

$display("Test complete");
end
endmodule

LAB2/QUES1/question1_tb.vcd
$date
	Sat Aug 10 09:25:14 2024
$end
$version
	Icarus Verilog
$end
$timescale
	1ns
$end
$scope module question1_tb $end
$var wire 1 ! f $end
$var reg 1 " A $end
$var reg 1 # B $end
$var reg 1 $ C $end
$var reg 1 % D $end
$scope module q1 $end
$var wire 1 " A $end
$var wire 1 # B $end
$var wire 1 $ C $end
$var wire 1 % D $end
$var wire 1 ! f $end
$var wire 1 & g $end
$var wire 1 ' h $end
$upscope $end
$upscope $end
$enddefinitions $end
#0
$dumpvars
1'
1&
0%
0$
0#
0"
1!
$end
#20
0!
0&
1%
#40
0%
1$
#60
1%
#80
1!
1&
0%
0$
1#
#100
0!
0&
1%
#120
0%
1$
#140
1%
#160
1!
1&
0%
0$
0#
1"
#180
0!
0&
1%
#200
0%
1$
#220
1%
#240
1&
0'
0%
0$
1#
#260
1!
0&
1%
#280
0%
1$
#300
1%
