LAB1/add2/A2.v
module A2(A,B,C,D,f);
input A,B,C,D;
output f;
assign f = (A & B & C)|(A & B & D)|(D & B & C)|(A & D & C);
endmodule

LAB1/add2/A2_tb.v
`timescale 1ns/1ns
`include "A2.v"

module A2_tb();
reg A,B,C,D;
wire f;

A2 plot(A,B,C,D,f);

initial
begin
$dumpfile("A2_tb.vcd");
$dumpvars(0, A2_tb);

A=1'b0; B=1'b0; C=1'b0; D=1'b0;
#20;
A=1'b0; B=1'b0; C=1'b0; D=1'b1;
#20;
A=1'b0; B=1'b0; C=1'b1; D=1'b0;
#20;
A=1'b0; B=1'b0; C=1'b1; D=1'b1;
#20;
A=1'b0; B=1'b1; C=1'b0; D=1'b0;
#20;
A=1'b0; B=1'b1; C=1'b0; D=1'b1;
#20;
A=1'b0; B=1'b1; C=1'b1; D=1'b0;
#20;
A=1'b0; B=1'b1; C=1'b1; D=1'b1;
#20;
A=1'b1; B=1'b0; C=1'b0; D=1'b0;
#20;
A=1'b1; B=1'b0; C=1'b0; D=1'b1;
#20;
A=1'b1; B=1'b0; C=1'b1; D=1'b0;
#20;
A=1'b1; B=1'b0; C=1'b1; D=1'b1;
#20;
A=1'b1; B=1'b1; C=1'b0; D=1'b0;
#20;
A=1'b1; B=1'b1; C=1'b0; D=1'b1;
#20;
A=1'b1; B=1'b1; C=1'b1; D=1'b0;
#20;
A=1'b1; B=1'b1; C=1'b1; D=1'b1;
#20;

$display("Test complete");
end
endmodule

LAB1/add2/A2_tb.vcd
$date
	Sat Aug  3 10:06:01 2024
$end
$version
	Icarus Verilog
$end
$timescale
	1ns
$end
$scope module A2_tb $end
$var wire 1 ! f $end
$var reg 1 " A $end
$var reg 1 # B $end
$var reg 1 $ C $end
$var reg 1 % D $end
$scope module plot $end
$var wire 1 " A $end
$var wire 1 # B $end
$var wire 1 $ C $end
$var wire 1 % D $end
$var wire 1 ! f $end
$upscope $end
$upscope $end
$enddefinitions $end
#0
$dumpvars
0%
0$
0#
0"
0!
$end
#20
1%
#40
0%
1$
#60
1%
#80
0%
0$
1#
#100
1%
#120
0!
0%
1$
#140
1!
1%
#160
0!
0%
0$
0#
1"
#180
1%
#200
0!
0%
1$
#220
1!
1%
#240
0!
0%
0$
1#
#260
1!
1%
#280
0%
1$
#300
1%
