LAB1/Q3/QUES3.v
module QUES3(A,B,C,D,f);
input A,B,C,D;
output f;
assign f = (C & ~D) |(C & ~A)|(C & ~B)|(B & ~C & D);
endmodule

LAB1/Q3/QUES3_tb.v
`timescale 1ns/1ns
`include "QUES3.v"

module QUES3_tb();
reg A,B,C,D;
wire f;

QUES3 plot(A,B,C,D,f);

initial
begin
$dumpfile("QUES3_tb.vcd");
$dumpvars(0, QUES3_tb);

A=1'b0; B=1'b0; C=1'b0; D=1'b0;
#20;
A=1'b0; B=1'b0; C=1'b0; D=1'b1;
#20;
A=1'b0; B=1'b0; C=1'b1; D=1'b0;
#20;
A=1'b0; B=1'b0; C=1'b1; D=1'b1;
#20;
A=1'b0; B=1'b1; C=1'b0; D=1'b0;
#20;
A=1'b0; B=1'b1; C=1'b0; D=1'b1;
#20;
A=1'b0; B=1'b1; C=1'b1; D=1'b0;
#20;
A=1'b0; B=1'b1; C=1'b1; D=1'b1;
#20;
A=1'b1; B=1'b0; C=1'b0; D=1'b0;
#20;
A=1'b1; B=1'b0; C=1'b0; D=1'b1;
#20;
A=1'b1; B=1'b0; C=1'b1; D=1'b0;
#20;
A=1'b1; B=1'b0; C=1'b1; D=1'b1;
#20;
A=1'b1; B=1'b1; C=1'b0; D=1'b0;
#20;
A=1'b1; B=1'b1; C=1'b0; D=1'b1;
#20;
A=1'b1; B=1'b1; C=1'b1; D=1'b0;
#20;
A=1'b1; B=1'b1; C=1'b1; D=1'b1;
#20;

$display("Test complete");
end
endmodule

LAB1/Q3/QUES3_tb.vcd
$date
	Sat Aug  3 09:30:36 2024
$end
$version
	Icarus Verilog
$end
$timescale
	1ns
$end
$scope module QUES3_tb $end
$var wire 1 ! f $end
$var reg 1 " A $end
$var reg 1 # B $end
$var reg 1 $ C $end
$var reg 1 % D $end
$scope module plot $end
$var wire 1 " A $end
$var wire 1 # B $end
$var wire 1 $ C $end
$var wire 1 % D $end
$var wire 1 ! f $end
$upscope $end
$upscope $end
$enddefinitions $end
#0
$dumpvars
0%
0$
0#
0"
0!
$end
#20
1%
#40
1!
0%
1$
#60
1%
#80
0!
0%
0$
1#
#100
1!
1%
#120
1!
0%
1$
#140
1%
#160
0!
0%
0$
0#
1"
#180
1%
#200
1!
0%
1$
#220
1%
#240
0!
0%
0$
1#
#260
1!
1%
#280
1!
0%
1$
#300
0!
1%
