LAB4/QUES3/pe4to2.v
module pe4to2(in,en,out);
input[3:0]in;
input en;
output reg[1:0]out;
always@(in,en)
begin
if(en==1)
   begin
casex(in)
4'b1XXX:out=2'b11;
#20;
4'b01XX:out=2'b10;
#20;
4'b001X:out=2'b01;
#20;
4'b0000:out=2'b00;
#20;
endcase
end
else
begin
out=2'b00;
end
end
endmodule

LAB4/QUES3/pe4to2_tb.v
`timescale 1ns/1ns
`include "pe4to2.v"
module pe4to2_tb;
reg[3:0]in;
reg en;
wire [1:0]out;
pe4to2 q(in,en,out);
initial
begin
$dumpfile("pe4to2_tb.vcd");
$dumpvars(0,pe4to2_tb);
en=1'b0 ;in=4'b0001 ;
#20;
en=1'b0 ;in=4'b0011 ;
#20;
en=1'b1 ;in=4'b0010 ;
#20;
en=1'b1 ;in=4'b1101 ;
#20;
en=1'b1 ;in=4'b0100 ;
#20;
en=1'b1 ;in=4'b1110 ;
#20;
en=1'b1 ;in=4'b0000 ;
#20;
en=1'b1 ;in=4'b1111 ;
#20;
$display("Test complete");
end
endmodule

LAB4/QUES3/pe4to2_tb.vcd
$date
	Sat Aug 31 10:40:08 2024
$end
$version
	Icarus Verilog
$end
$timescale
	1ns
$end
$scope module pe4to2_tb $end
$var wire 2 ! out [1:0] $end
$var reg 1 " en $end
$var reg 4 # in [3:0] $end
$scope module q $end
$var wire 1 " en $end
$var wire 4 $ in [3:0] $end
$var reg 2 % out [1:0] $end
$upscope $end
$upscope $end
$enddefinitions $end
#0
$dumpvars
b0 %
b1 $
b1 #
0"
b0 !
$end
#20
b11 #
b11 $
#40
b1 !
b1 %
b10 #
b10 $
1"
#60
b11 !
b11 %
b1101 #
b1101 $
#80
b10 !
b10 %
b100 #
b100 $
#100
b11 !
b11 %
b1110 #
b1110 $
#120
b0 !
b0 %
b0 #
b0 $
#140
b11 !
b11 %
b1111 #
b1111 $
