LAB3/mux4to1/mux4to1.v
module mux4to1(w0,w1,w2,w3,s,f);
input w0,w1,w2,w3;
input [1:0]s;
output reg f;
always @ (w0,w1,w2,w3,s)begin
if(s==2'b00)
begin f=w0;end
else if(s==2'b01)
begin f=w1;end
else if(s==2'b10)
begin f=w2;end
else
begin f=w3;end
end
endmodule

LAB3/mux4to1/mux4to1_tb.v
`timescale 1ns/1ns
`include "mux4to1.v"
module mux4to1_tb();
reg w0,w1,w2,w3;
reg [1:0]s;
wire f;
mux4to1 mux1(w0,w1,w2,w3,s,f);
initial 
begin
$dumpfile("mux4to1_tb.vcd");
$dumpvars(0,mux4to1_tb);
s=2'b00; w0=1'b1 ; w1=1'b0 ; w2=1'b0 ; w3=1'b0 ;
#20;
s=2'b01; w0=1'b0 ; w1=1'b1 ; w2=1'b0 ; w3=1'b0 ;
#20;
s=2'b10; w0=1'b0 ; w1=1'b0 ; w2=1'b1 ; w3=1'b0 ;
#20;
s=2'b11; w0=1'b0 ; w1=1'b0 ; w2=1'b0 ; w3=1'b1 ;
#20;
s=2'b00; w0=1'b0  ; w1=1'b1 ; w2=1'b1 ; w3=1'b1 ;
#20;
s=2'b01; w0=1'b1  ; w1=1'b0 ; w2=1'b1 ; w3=1'b1 ;
#20;
s=2'b10; w0=1'b1 ; w1=1'b1 ; w2=1'b0 ; w3=1'b1 ;
#20;
s=2'b11; w0=1'b1  ; w1=1'b1 ; w2=1'b1 ; w3=1'b0 ;
#20;

$display("Test complete");
end
endmodule

LAB3/mux4to1/mux4to1_tb.vcd
$date
	Sat Aug 24 09:58:27 2024
$end
$version
	Icarus Verilog
$end
$timescale
	1ns
$end
$scope module mux4to1_tb $end
$var wire 1 ! f $end
$var reg 2 " s [1:0] $end
$var reg 1 # w0 $end
$var reg 1 $ w1 $end
$var reg 1 % w2 $end
$var reg 1 & w3 $end
$scope module mux1 $end
$var wire 2 ' s [1:0] $end
$var wire 1 # w0 $end
$var wire 1 $ w1 $end
$var wire 1 % w2 $end
$var wire 1 & w3 $end
$var reg 1 ! f $end
$upscope $end
$upscope $end
$enddefinitions $end
#0
$dumpvars
b0 '
0&
0%
0$
1#
b0 "
1!
$end
#20
1$
0#
b1 "
b1 '
#40
1%
0$
b10 "
b10 '
#60
1&
0%
b11 "
b11 '
#80
0!
1%
1$
b0 "
b0 '
#100
0$
1#
b1 "
b1 '
#120
0%
1$
b10 "
b10 '
#140
0&
1%
b11 "
b11 '
