LAB5/Q1/mux4to1.v
module mux4to1(ab,c,d,f);
input [1:0]ab;
input c,d;
output reg f;
always@(*)
begin
case(ab)
2'b00:f=~c|~d;
2'b01:f=~d;
2'b10:f=~c & d;
2'b11:f=~d;
default:f=1'b0;
endcase
end
endmodule

LAB5/Q1/mux4to1_tb.v
`timescale 1ns/1ns
`include "mux4to1.v"
module mux4to1_tb();
reg [1:0]ab;
reg c,d;
wire f;
mux4to1 mux(ab,c,d,f);
initial
begin
$dumpfile("mux4to1_tb.vcd");
$dumpvars(0,mux4to1_tb);

ab=2'b00;c=1'b0;d=1'b0;#10;
ab=2'b00;c=1'b0;d=1'b1;#10;
ab=2'b00;c=1'b1;d=1'b0;#10;
ab=2'b00;c=1'b1;d=1'b1;#10;
ab=2'b01;c=1'b0;d=1'b0;#10;
ab=2'b01;c=1'b0;d=1'b1;#10;
ab=2'b01;c=1'b1;d=1'b0;#10;
ab=2'b01;c=1'b1;d=1'b1;#10;
ab=2'b10;c=1'b0;d=1'b0;#10;
ab=2'b10;c=1'b0;d=1'b1;#10;
ab=2'b10;c=1'b1;d=1'b0;#10;
ab=2'b10;c=1'b1;d=1'b1;#10;
ab=2'b11;c=1'b0;d=1'b0;#10;
ab=2'b11;c=1'b0;d=1'b1;#10;
ab=2'b11;c=1'b1;d=1'b0;#10;
ab=2'b11;c=1'b1;d=1'b1;#10;

$display("Test Complete");
end
endmodule

LAB5/Q1/mux4to1_tb.vcd
$date
	Mon Sep  2 09:58:17 2024
$end
$version
	Icarus Verilog
$end
$timescale
	1ns
$end
$scope module mux4to1_tb $end
$var wire 1 ! f $end
$var reg 2 " ab [1:0] $end
$var reg 1 # c $end
$var reg 1 $ d $end
$scope module mux $end
$var wire 2 % ab [1:0] $end
$var wire 1 # c $end
$var wire 1 $ d $end
$var reg 1 ! f $end
$upscope $end
$upscope $end
$enddefinitions $end
#0
$dumpvars
b0 %
0$
0#
b0 "
1!
$end
#10
1$
#20
0$
1#
#30
0!
1$
#40
1!
0$
0#
b1 "
b1 %
#50
0!
1$
#60
1!
0$
1#
#70
0!
1$
#80
0$
0#
b10 "
b10 %
#90
1!
1$
#100
0!
0$
1#
#110
1$
#120
1!
0$
0#
b11 "
b11 %
#130
0!
1$
#140
1!
0$
1#
#150
0!
1$
