LAB5/Q2/graytobin.v
module mux8to1(
    input[2:0] s,
    input in0, in1, in2, in3, in4, in5, in6, in7,
    output reg op
);
    always @(*) begin
        case(s)
            1:op = in0;
            2:op = in1;
            3:op = in2;
            4:op = in3;
            5:op = in4;
            6:op = in5;
            7:op = in6;
            8:op = in7;
            default: op = 1'b0;
        endcase
    end
endmodule

module graytobin(
    input [3:0] g,
    output [3:0] b
);
    mux8to1 m3(g[3:1], 1'b0, 1'b0, 1'b0, 1'b0, 1'b1, 1'b1, 1'b1, 1'b1, b[3]);
    mux8to1 m2(g[3:1], 1'b0, 1'b0, 1'b1, 1'b1, 1'b1, 1'b1, 1'b0, 1'b0, b[2]);
    mux8to1 m1(g[3:1], 1'b0, 1'b1, 1'b1, 1'b0, 1'b1, 1'b0, 1'b0, 1'b1, b[1]);
    mux8to1 m0(g[3:1], g[0], ~g[0], ~g[0], g[0], ~g[0], g[0], g[0], ~g[0], b[0]);
endmodule

LAB5/Q2/graytobin_tb.v
`timescale 1ns/1ns
`include "graytobin.v"
module graytobin_tb();
reg [3:0]g;
wire [3:0]b;
graytobin gtb(g,b);
initial
begin
$dumpfile("graytobin_tb.vcd");
$dumpvars(0,graytobin_tb);

g=4'b0000;#20;
g=4'b0001;#20;
g=4'b0010;#20;
g=4'b0011;#20;
g=4'b0100;#20;
g=4'b0101;#20;
g=4'b0110;#20;
g=4'b0111;#20;
g=4'b1000;#20;

$display("Test Complete");
end
endmodule

LAB5/Q2/graytobin_tb.vcd
$date
	Mon Sep  2 11:03:52 2024
$end
$version
	Icarus Verilog
$end
$timescale
	1ns
$end
$scope module graytobin_tb $end
$var wire 4 ! b [3:0] $end
$var reg 4 " g [3:0] $end
$scope module gtb $end
$var wire 4 # g [3:0] $end
$var wire 4 $ b [3:0] $end
$scope module m0 $end
$var wire 1 % in0 $end
$var wire 1 & in1 $end
$var wire 1 ' in2 $end
$var wire 1 ( in3 $end
$var wire 1 ) in4 $end
$var wire 1 * in5 $end
$var wire 1 + in6 $end
$var wire 1 , in7 $end
$var wire 3 - s [2:0] $end
$var reg 1 . op $end
$upscope $end
$scope module m1 $end
$var wire 1 / in0 $end
$var wire 1 0 in1 $end
$var wire 1 1 in2 $end
$var wire 1 2 in3 $end
$var wire 1 3 in4 $end
$var wire 1 4 in5 $end
$var wire 1 5 in6 $end
$var wire 1 6 in7 $end
$var wire 3 7 s [2:0] $end
$var reg 1 8 op $end
$upscope $end
$scope module m2 $end
$var wire 1 9 in0 $end
$var wire 1 : in1 $end
$var wire 1 ; in2 $end
$var wire 1 < in3 $end
$var wire 1 = in4 $end
$var wire 1 > in5 $end
$var wire 1 ? in6 $end
$var wire 1 @ in7 $end
$var wire 3 A s [2:0] $end
$var reg 1 B op $end
$upscope $end
$scope module m3 $end
$var wire 1 C in0 $end
$var wire 1 D in1 $end
$var wire 1 E in2 $end
$var wire 1 F in3 $end
$var wire 1 G in4 $end
$var wire 1 H in5 $end
$var wire 1 I in6 $end
$var wire 1 J in7 $end
$var wire 3 K s [2:0] $end
$var reg 1 L op $end
$upscope $end
$upscope $end
$upscope $end
$enddefinitions $end
#0
$dumpvars
0L
b0 K
1J
1I
1H
1G
0F
0E
0D
0C
0B
b0 A
0@
0?
1>
1=
1<
1;
0:
09
08
b0 7
16
05
04
13
02
11
10
0/
0.
b0 -
1,
0+
0*
1)
0(
1'
1&
0%
b0 $
b0 #
b0 "
b0 !
$end
#20
0&
0'
0)
0,
1%
1(
1*
1+
b1 "
b1 #
#40
1&
1'
1)
1,
b1 K
b1 A
b1 7
b1 -
0%
0(
0*
0+
b10 "
b10 #
#60
0&
0'
0)
b1 !
b1 $
1.
0,
1%
1(
1*
1+
b11 "
b11 #
#80
18
1&
1'
1)
b11 !
b11 $
1.
1,
b10 K
b10 A
b10 7
b10 -
0%
0(
0*
0+
b100 "
b100 #
#100
b10 !
b10 $
0.
0&
0'
0)
0,
1%
1(
1*
1+
b101 "
b101 #
#120
1.
b111 !
b111 $
1B
1&
1'
1)
1,
b11 K
b11 A
b11 7
b11 -
0%
0(
0*
0+
b110 "
b110 #
#140
b110 !
b110 $
0.
0&
0'
0)
0,
1%
1(
1*
1+
b111 "
b111 #
#160
b100 !
b100 $
08
1&
1'
1)
1,
b100 K
b100 A
b100 7
b100 -
0%
0(
0*
0+
b1000 "
b1000 #
