LAB3/EXAMPLE/ex.v
module ex (w0, w1, s, f);
input w0, w1, s;
output f;
reg f;
always @(w0 or w1 or s)
f = s ? w1 : w0;
endmodule

LAB3/EXAMPLE/ex_tb.v
`timescale 1ns/1ns
`include "ex.v"
module ex_tb();
reg x1,x2,s;
wire f;
ex ex2(x1,x2,s,f);
initial
begin
$dumpfile("ex_tb.vcd");
$dumpvars(0,ex_tb);
s=1'b0;x1=1'b0;x2=1'b0;
#20;
s=1'b0;x1=1'b0;x2=1'b1;
#20;
s=1'b0;x1=1'b1;x2=1'b0;
#20;
s=1'b0;x1=1'b1;x2=1'b1;
#20;
s=1'b1;x1=1'b0;x2=1'b0;
#20;
s=1'b1;x1=1'b0;x2=1'b1;
#20;
s=1'b1;x1=1'b1;x2=1'b0;
#20;
s=1'b1;x1=1'b1;x2=1'b1;
#20;
$display("test Complete");
end
endmodule

LAB3/EXAMPLE/ex_tb.vcd
$date
	Sat Aug 24 09:14:32 2024
$end
$version
	Icarus Verilog
$end
$timescale
	1ns
$end
$scope module ex_tb $end
$var wire 1 ! f $end
$var reg 1 " s $end
$var reg 1 # x1 $end
$var reg 1 $ x2 $end
$scope module ex2 $end
$var wire 1 " s $end
$var wire 1 # w0 $end
$var wire 1 $ w1 $end
$var reg 1 ! f $end
$upscope $end
$upscope $end
$enddefinitions $end
#0
$dumpvars
0$
0#
0"
0!
$end
#20
1$
#40
1!
0$
1#
#60
1$
#80
0!
0$
0#
1"
#100
1!
1$
#120
0!
0$
1#
#140
1!
1$
